/*
 * Copyright (c) 2026 Enaium
 *
 * Permission is hereby granted, free of charge, to any person obtaining a copy
 * of this software and associated documentation files (the "Software"), to deal
 * in the Software without restriction, including without limitation the rights
 * to use, copy, modify, merge, publish, distribute, sublicense, and/or sell
 * copies of the Software, and to permit persons to whom the Software is
 * furnished to do so, subject to the following conditions:
 *
 * The above copyright notice and this permission notice shall be included in all
 * copies or substantial portions of the Software.
 *
 * THE SOFTWARE IS PROVIDED "AS IS", WITHOUT WARRANTY OF ANY KIND, EXPRESS OR
 * IMPLIED, INCLUDING BUT NOT LIMITED TO THE WARRANTIES OF MERCHANTABILITY,
 * FITNESS FOR A PARTICULAR PURPOSE AND NONINFRINGEMENT. IN NO EVENT SHALL THE
 * AUTHORS OR COPYRIGHT HOLDERS BE LIABLE FOR ANY CLAIM, DAMAGES OR OTHER
 * LIABILITY, WHETHER IN AN ACTION OF CONTRACT, TORT OR OTHERWISE, ARISING FROM,
 * OUT OF OR IN CONNECTION WITH THE SOFTWARE OR THE USE OR OTHER DEALINGS IN THE
 * SOFTWARE.
 */

const ACC_PUBLIC = 0x0001;
const ACC_PRIVATE = 0x0002;
const ACC_PROTECTED = 0x0004;
const ACC_STATIC = 0x0008;
const ACC_FINAL = 0x0010;

const NOP = 0;
const ACONST_NULL = 1;
const ICONST_M1 = 2;
const ICONST_0 = 3;
const ICONST_1 = 4;
const ICONST_2 = 5;
const ICONST_3 = 6;
const ICONST_4 = 7;
const ICONST_5 = 8;
const LCONST_0 = 9;
const LCONST_1 = 10;
const FCONST_0 = 11;
const FCONST_1 = 12;
const FCONST_2 = 13;
const DCONST_0 = 14;
const DCONST_1 = 15;
const BIPUSH = 16;
const SIPUSH = 17;
const LDC = 18;
const ILOAD = 21;
const LLOAD = 22;
const FLOAD = 23;
const DLOAD = 24;
const ALOAD = 25;
const IALOAD = 46;
const LALOAD = 47;
const FALOAD = 48;
const DALOAD = 49;
const AALOAD = 50;
const BALOAD = 51;
const CALOAD = 52;
const SALOAD = 53;
const ISTORE = 54;
const LSTORE = 55;
const FSTORE = 56;
const DSTORE = 57;
const ASTORE = 58;
const IASTORE = 79;
const LASTORE = 80;
const FASTORE = 81;
const DASTORE = 82;
const AASTORE = 83;
const BASTORE = 84;
const CASTORE = 85;
const SASTORE = 86;
const POP = 87;
const POP2 = 88;
const DUP = 89;
const DUP_X1 = 90;
const DUP_X2 = 91;
const DUP2 = 92;
const DUP2_X1 = 93;
const DUP2_X2 = 94;
const SWAP = 95;
const IADD = 96;
const LADD = 97;
const FADD = 98;
const DADD = 99;
const ISUB = 100;
const LSUB = 101;
const FSUB = 102;
const DSUB = 103;
const IMUL = 104;
const LMUL = 105;
const FMUL = 106;
const DMUL = 107;
const IDIV = 108;
const LDIV = 109;
const FDIV = 110;
const DDIV = 111;
const IREM = 112;
const LREM = 113;
const FREM = 114;
const DREM = 115;
const INEG = 116;
const LNEG = 117;
const FNEG = 118;
const DNEG = 119;
const ISHL = 120;
const LSHL = 121;
const ISHR = 122;
const LSHR = 123;
const IUSHR = 124;
const LUSHR = 125;
const IAND = 126;
const LAND = 127;
const IOR = 128;
const LOR = 129;
const IXOR = 130;
const LXOR = 131;
const IINC = 132;
const I2L = 133;
const I2F = 134;
const I2D = 135;
const L2I = 136;
const L2F = 137;
const L2D = 138;
const F2I = 139;
const F2L = 140;
const F2D = 141;
const D2I = 142;
const D2L = 143;
const D2F = 144;
const I2B = 145;
const I2C = 146;
const I2S = 147;
const LCMP = 148;
const FCMPL = 149;
const FCMPG = 150;
const DCMPL = 151;
const DCMPG = 152;
const IFEQ = 153;
const IFNE = 154;
const IFLT = 155;
const IFGE = 156;
const IFGT = 157;
const IFLE = 158;
const IF_ICMPEQ = 159;
const IF_ICMPNE = 160;
const IF_ICMPLT = 161;
const IF_ICMPGE = 162;
const IF_ICMPGT = 163;
const IF_ICMPLE = 164;
const IF_ACMPEQ = 165;
const IF_ACMPNE = 166;
const GOTO = 167;
const JSR = 168;
const RET = 169;
const TABLESWITCH = 170;
const LOOKUPSWITCH = 171;
const IRETURN = 172;
const LRETURN = 173;
const FRETURN = 174;
const DRETURN = 175;
const ARETURN = 176;
const RETURN = 177;
const GETSTATIC = 178;
const PUTSTATIC = 179;
const GETFIELD = 180;
const PUTFIELD = 181;
const INVOKEVIRTUAL = 182;
const INVOKESPECIAL = 183;
const INVOKESTATIC = 184;
const INVOKEINTERFACE = 185;
const INVOKEDYNAMIC = 186;
const NEW = 187;
const NEWARRAY = 188;
const ANEWARRAY = 189;
const ARRAYLENGTH = 190;
const ATHROW = 191;
const CHECKCAST = 192;
const INSTANCEOF = 193;
const MONITORENTER = 194;
const MONITOREXIT = 195;
const MULTIANEWARRAY = 197;
const IFNULL = 198;
const IFNONNULL = 199;

const opcodes = [
  'NOP', // 0 (0x0)
  'ACONST_NULL', // 1 (0x1)
  'ICONST_M1', // 2 (0x2)
  'ICONST_0', // 3 (0x3)
  'ICONST_1', // 4 (0x4)
  'ICONST_2', // 5 (0x5)
  'ICONST_3', // 6 (0x6)
  'ICONST_4', // 7 (0x7)
  'ICONST_5', // 8 (0x8)
  'LCONST_0', // 9 (0x9)
  'LCONST_1', // 10 (0xa)
  'FCONST_0', // 11 (0xb)
  'FCONST_1', // 12 (0xc)
  'FCONST_2', // 13 (0xd)
  'DCONST_0', // 14 (0xe)
  'DCONST_1', // 15 (0xf)
  'BIPUSH', // 16 (0x10)
  'SIPUSH', // 17 (0x11)
  'LDC', // 18 (0x12)
  'LDC_W', // 19 (0x13)
  'LDC2_W', // 20 (0x14)
  'ILOAD', // 21 (0x15)
  'LLOAD', // 22 (0x16)
  'FLOAD', // 23 (0x17)
  'DLOAD', // 24 (0x18)
  'ALOAD', // 25 (0x19)
  'ILOAD_0', // 26 (0x1a)
  'ILOAD_1', // 27 (0x1b)
  'ILOAD_2', // 28 (0x1c)
  'ILOAD_3', // 29 (0x1d)
  'LLOAD_0', // 30 (0x1e)
  'LLOAD_1', // 31 (0x1f)
  'LLOAD_2', // 32 (0x20)
  'LLOAD_3', // 33 (0x21)
  'FLOAD_0', // 34 (0x22)
  'FLOAD_1', // 35 (0x23)
  'FLOAD_2', // 36 (0x24)
  'FLOAD_3', // 37 (0x25)
  'DLOAD_0', // 38 (0x26)
  'DLOAD_1', // 39 (0x27)
  'DLOAD_2', // 40 (0x28)
  'DLOAD_3', // 41 (0x29)
  'ALOAD_0', // 42 (0x2a)
  'ALOAD_1', // 43 (0x2b)
  'ALOAD_2', // 44 (0x2c)
  'ALOAD_3', // 45 (0x2d)
  'IALOAD', // 46 (0x2e)
  'LALOAD', // 47 (0x2f)
  'FALOAD', // 48 (0x30)
  'DALOAD', // 49 (0x31)
  'AALOAD', // 50 (0x32)
  'BALOAD', // 51 (0x33)
  'CALOAD', // 52 (0x34)
  'SALOAD', // 53 (0x35)
  'ISTORE', // 54 (0x36)
  'LSTORE', // 55 (0x37)
  'FSTORE', // 56 (0x38)
  'DSTORE', // 57 (0x39)
  'ASTORE', // 58 (0x3a)
  'ISTORE_0', // 59 (0x3b)
  'ISTORE_1', // 60 (0x3c)
  'ISTORE_2', // 61 (0x3d)
  'ISTORE_3', // 62 (0x3e)
  'LSTORE_0', // 63 (0x3f)
  'LSTORE_1', // 64 (0x40)
  'LSTORE_2', // 65 (0x41)
  'LSTORE_3', // 66 (0x42)
  'FSTORE_0', // 67 (0x43)
  'FSTORE_1', // 68 (0x44)
  'FSTORE_2', // 69 (0x45)
  'FSTORE_3', // 70 (0x46)
  'DSTORE_0', // 71 (0x47)
  'DSTORE_1', // 72 (0x48)
  'DSTORE_2', // 73 (0x49)
  'DSTORE_3', // 74 (0x4a)
  'ASTORE_0', // 75 (0x4b)
  'ASTORE_1', // 76 (0x4c)
  'ASTORE_2', // 77 (0x4d)
  'ASTORE_3', // 78 (0x4e)
  'IASTORE', // 79 (0x4f)
  'LASTORE', // 80 (0x50)
  'FASTORE', // 81 (0x51)
  'DASTORE', // 82 (0x52)
  'AASTORE', // 83 (0x53)
  'BASTORE', // 84 (0x54)
  'CASTORE', // 85 (0x55)
  'SASTORE', // 86 (0x56)
  'POP', // 87 (0x57)
  'POP2', // 88 (0x58)
  'DUP', // 89 (0x59)
  'DUP_X1', // 90 (0x5a)
  'DUP_X2', // 91 (0x5b)
  'DUP2', // 92 (0x5c)
  'DUP2_X1', // 93 (0x5d)
  'DUP2_X2', // 94 (0x5e)
  'SWAP', // 95 (0x5f)
  'IADD', // 96 (0x60)
  'LADD', // 97 (0x61)
  'FADD', // 98 (0x62)
  'DADD', // 99 (0x63)
  'ISUB', // 100 (0x64)
  'LSUB', // 101 (0x65)
  'FSUB', // 102 (0x66)
  'DSUB', // 103 (0x67)
  'IMUL', // 104 (0x68)
  'LMUL', // 105 (0x69)
  'FMUL', // 106 (0x6a)
  'DMUL', // 107 (0x6b)
  'IDIV', // 108 (0x6c)
  'LDIV', // 109 (0x6d)
  'FDIV', // 110 (0x6e)
  'DDIV', // 111 (0x6f)
  'IREM', // 112 (0x70)
  'LREM', // 113 (0x71)
  'FREM', // 114 (0x72)
  'DREM', // 115 (0x73)
  'INEG', // 116 (0x74)
  'LNEG', // 117 (0x75)
  'FNEG', // 118 (0x76)
  'DNEG', // 119 (0x77)
  'ISHL', // 120 (0x78)
  'LSHL', // 121 (0x79)
  'ISHR', // 122 (0x7a)
  'LSHR', // 123 (0x7b)
  'IUSHR', // 124 (0x7c)
  'LUSHR', // 125 (0x7d)
  'IAND', // 126 (0x7e)
  'LAND', // 127 (0x7f)
  'IOR', // 128 (0x80)
  'LOR', // 129 (0x81)
  'IXOR', // 130 (0x82)
  'LXOR', // 131 (0x83)
  'IINC', // 132 (0x84)
  'I2L', // 133 (0x85)
  'I2F', // 134 (0x86)
  'I2D', // 135 (0x87)
  'L2I', // 136 (0x88)
  'L2F', // 137 (0x89)
  'L2D', // 138 (0x8a)
  'F2I', // 139 (0x8b)
  'F2L', // 140 (0x8c)
  'F2D', // 141 (0x8d)
  'D2I', // 142 (0x8e)
  'D2L', // 143 (0x8f)
  'D2F', // 144 (0x90)
  'I2B', // 145 (0x91)
  'I2C', // 146 (0x92)
  'I2S', // 147 (0x93)
  'LCMP', // 148 (0x94)
  'FCMPL', // 149 (0x95)
  'FCMPG', // 150 (0x96)
  'DCMPL', // 151 (0x97)
  'DCMPG', // 152 (0x98)
  'IFEQ', // 153 (0x99)
  'IFNE', // 154 (0x9a)
  'IFLT', // 155 (0x9b)
  'IFGE', // 156 (0x9c)
  'IFGT', // 157 (0x9d)
  'IFLE', // 158 (0x9e)
  'IF_ICMPEQ', // 159 (0x9f)
  'IF_ICMPNE', // 160 (0xa0)
  'IF_ICMPLT', // 161 (0xa1)
  'IF_ICMPGE', // 162 (0xa2)
  'IF_ICMPGT', // 163 (0xa3)
  'IF_ICMPLE', // 164 (0xa4)
  'IF_ACMPEQ', // 165 (0xa5)
  'IF_ACMPNE', // 166 (0xa6)
  'GOTO', // 167 (0xa7)
  'JSR', // 168 (0xa8)
  'RET', // 169 (0xa9)
  'TABLESWITCH', // 170 (0xaa)
  'LOOKUPSWITCH', // 171 (0xab)
  'IRETURN', // 172 (0xac)
  'LRETURN', // 173 (0xad)
  'FRETURN', // 174 (0xae)
  'DRETURN', // 175 (0xaf)
  'ARETURN', // 176 (0xb0)
  'RETURN', // 177 (0xb1)
  'GETSTATIC', // 178 (0xb2)
  'PUTSTATIC', // 179 (0xb3)
  'GETFIELD', // 180 (0xb4)
  'PUTFIELD', // 181 (0xb5)
  'INVOKEVIRTUAL', // 182 (0xb6)
  'INVOKESPECIAL', // 183 (0xb7)
  'INVOKESTATIC', // 184 (0xb8)
  'INVOKEINTERFACE', // 185 (0xb9)
  'INVOKEDYNAMIC', // 186 (0xba)
  'NEW', // 187 (0xbb)
  'NEWARRAY', // 188 (0xbc)
  'ANEWARRAY', // 189 (0xbd)
  'ARRAYLENGTH', // 190 (0xbe)
  'ATHROW', // 191 (0xbf)
  'CHECKCAST', // 192 (0xc0)
  'INSTANCEOF', // 193 (0xc1)
  'MONITORENTER', // 194 (0xc2)
  'MONITOREXIT', // 195 (0xc3)
  'WIDE', // 196 (0xc4)
  'MULTIANEWARRAY', // 197 (0xc5)
  'IFNULL', // 198 (0xc6)
  'IFNONNULL', // 199 (0xc7)
];

const INSN = 0;
const INT_INSN = 1;
const VAR_INSN = 2;
const TYPE_INSN = 3;
const FIELD_INSN = 4;
const METHOD_INSN = 5;
const INVOKE_DYNAMIC_INSN = 6;
const JUMP_INSN = 7;
const LABEL = 8;
const LDC_INSN = 9;
const IINC_INSN = 10;
const TABLESWITCH_INSN = 11;
const LOOKUPSWITCH_INSN = 12;
const MULTIANEWARRAY_INSN = 13;
const FRAME = 14;
const LINE = 15;

const F_NEW = -1;
const F_FULL = 0;
const F_APPEND = 1;
const F_CHOP = 2;
const F_SAME = 3;
const F_SAME1 = 4;
